CHANGES.txt
LICENSE.txt
MANIFEST.in
README.txt
setup.py
js/__init__.py
js.modernizr.egg-info/PKG-INFO
js.modernizr.egg-info/SOURCES.txt
js.modernizr.egg-info/dependency_links.txt
js.modernizr.egg-info/entry_points.txt
js.modernizr.egg-info/namespace_packages.txt
js.modernizr.egg-info/not-zip-safe
js.modernizr.egg-info/requires.txt
js.modernizr.egg-info/top_level.txt
js/modernizr/__init__.py
js/modernizr/test_modernizr.txt
js/modernizr/resources/modernizr-min.js
js/modernizr/resources/modernizr.js