Metadata-Version: 1.0
Name: js.modernizr
Version: 2.5.3.1
Summary: Fanstatic packaging of Modernizr
Home-page: UNKNOWN
Author: Fanstatic Developers
Author-email: fanstatic@googlegroups.com
License: BSD
Platform: UNKNOWN
